gsn/__init__.py
gsn/sensor.py
gsn-0.2.0.dist-info/DESCRIPTION.rst
gsn-0.2.0.dist-info/METADATA
gsn-0.2.0.dist-info/RECORD
gsn-0.2.0.dist-info/WHEEL
gsn-0.2.0.dist-info/metadata.json
gsn-0.2.0.dist-info/top_level.txt
